Metadata-Version: 2.1
Name: reg4opt
Version: 0.1.0
Summary: reg4opt
Home-page: https://github.com/nicola-bastianello/reg4opt
Author: Nicola Bastianello
Author-email: nicola.bastianello.3@phd.unipd.it
License: UNKNOWN
Platform: UNKNOWN
Classifier: Programming Language :: Python :: 3
Classifier: License :: OSI Approved :: GNU General Public License v3 (GPLv3)
Classifier: Operating System :: OS Independent
Requires-Python: >=3.7
